2.1__init__.py
CHANGELOG.txt
License.txt
MANIFEST.in
README.txt
Setup.py
setup.py
Dhiraj.egg-info/PKG-INFO
Dhiraj.egg-info/SOURCES.txt
Dhiraj.egg-info/dependency_links.txt
Dhiraj.egg-info/top_level.txt